semantic_filter/__init__.py
semantic_filter/filters.py
semantic_filter/filterset.py
django_semantic_filter-0.1.1.dist-info/METADATA
django_semantic_filter-0.1.1.dist-info/WHEEL
django_semantic_filter-0.1.1.dist-info/RECORD
