Metadata-Version: 2.1
Name: django-semantic-filter
Version: 0.1.1
Summary: Django Semantic UI for filtering Django QuerySets based on user selections
Home-page: https://github.com/globophobe/django-semantic-filter
License: MIT
Keywords: django,semantic,filter
Author: Alex
Author-email: globophobe@gmail.com
Requires-Python: >=3.8
Classifier: Development Status :: 4 - Beta
Classifier: Framework :: Django
Classifier: License :: OSI Approved :: MIT License
Classifier: Operating System :: OS Independent
Classifier: Programming Language :: Python :: 3
Classifier: Programming Language :: Python :: 3.8
Classifier: Programming Language :: Python :: 3.9
Classifier: Programming Language :: Python :: 3.10
Classifier: Programming Language :: Python :: 3.11
Requires-Dist: django-filter
Requires-Dist: django-semantic-forms
Project-URL: Repository, https://github.com/globophobe/django-semantic-filter
